README.md
setup.py
neptune_resolver_default/__init__.py
neptune_resolver_default/connect.py
neptune_resolver_default/resolver.py
neptune_resolver_default.egg-info/PKG-INFO
neptune_resolver_default.egg-info/SOURCES.txt
neptune_resolver_default.egg-info/dependency_links.txt
neptune_resolver_default.egg-info/requires.txt
neptune_resolver_default.egg-info/top_level.txt