Metadata-Version: 2.1
Name: neptune-resolver-default
Version: 2019.9.17.1706
Summary: DNS Resolver for Neptune DNS server
Home-page: https://git.best-service.online/yurzs/triton
Author: Yury (Yurzs)
Author-email: dev@best-service.online
License: MIT
Keywords: neptune,DNS,resolver
Platform: UNKNOWN
Classifier: Development Status :: 3 - Alpha
Classifier: Intended Audience :: Developers
Classifier: Topic :: Software Development :: Build Tools
Classifier: License :: OSI Approved :: MIT License
Classifier: Programming Language :: Python :: 3
Classifier: Programming Language :: Python :: 3.7
